radsdata/__init__.py
radsdata/user.py
radsreq/jwtbearer.py
radsreq/user.py
radsutils/__init__.py
radsutils/hamail.py
radsutils/logger.py
radsutils/mongo.py
radsutils/web.py
rad_sdk-0.0.1.dist-info/LICENSE
rad_sdk-0.0.1.dist-info/METADATA
rad_sdk-0.0.1.dist-info/WHEEL
rad_sdk-0.0.1.dist-info/top_level.txt
rad_sdk-0.0.1.dist-info/RECORD
