Metadata-Version: 2.1
Name: rad-sdk
Version: 0.0.1
Summary: Reverse Ads common Data Models
Home-page: https://github.com/reversead/rad-sdk
Author: Nayana Hettiarachchi
Author-email: nayana@reverseads.com
License: BSD 2-clause
Classifier: Programming Language :: Python :: 3.10
License-File: LICENSE
Requires-Dist: mongoengine (==0.24.2)
Requires-Dist: pydantic (==1.10.2)
Requires-Dist: boto3 (~=1.24.91)
Requires-Dist: botocore (~=1.27.91)
Requires-Dist: python-dotenv (~=0.21.0)
Requires-Dist: pika (~=1.3.0)
Requires-Dist: fastapi (~=0.85.0)
Requires-Dist: pyjwt (~=2.5.0)
Requires-Dist: deepgram-sdk (==1.0.0)
Requires-Dist: uvicorn (~=0.18.3)
Requires-Dist: Jinja2 (~=3.1.2)
Requires-Dist: slack-sdk (~=3.19.1)
Requires-Dist: pyhumps (~=3.7.3)
